gitcloakd/__init__.py
gitcloakd/api.py
gitcloakd/agents/__init__.py
gitcloakd/agents/manager.py
gitcloakd/alerts/__init__.py
gitcloakd/alerts/notifier.py
gitcloakd/cli/__init__.py
gitcloakd/cli/main.py
gitcloakd/core/__init__.py
gitcloakd/core/audit_log.py
gitcloakd/core/config.py
gitcloakd/core/dark_mode.py
gitcloakd/core/encryption.py
gitcloakd/core/full_encryption.py
gitcloakd/core/memory_cleaner.py
gitcloakd/core/scanner.py
gitcloakd/core/secure_storage.py
gitcloakd/crypto/__init__.py
gitcloakd/crypto/gpg.py
gitcloakd/data/banner.txt
gitcloakd/github/__init__.py
gitcloakd/github/analyzer.py
gitcloakd/github/client.py
gitcloakd/web/__init__.py
gitcloakd-1.0.11.dist-info/licenses/LICENSE
gitcloakd-1.0.11.dist-info/METADATA
gitcloakd-1.0.11.dist-info/WHEEL
gitcloakd-1.0.11.dist-info/entry_points.txt
gitcloakd-1.0.11.dist-info/top_level.txt
gitcloakd-1.0.11.dist-info/RECORD
