Metadata-Version: 2.4
Name: gitcloakd
Version: 1.0.11
Summary: Cloak Git repositories with GPG encryption - hide your code in plain sight
Author-email: "HaKC.dev" <dev@hakc.dev>
Maintainer-email: "HaKC.dev" <dev@hakc.dev>
License: MIT
Project-URL: Homepage, https://github.com/haKC-ai/gitcloakd
Project-URL: Documentation, https://github.com/haKC-ai/gitcloakd#readme
Project-URL: Repository, https://github.com/haKC-ai/gitcloakd
Project-URL: Issues, https://github.com/haKC-ai/gitcloakd/issues
Keywords: git,encryption,gpg,pgp,security,github,git-crypt,secrets,repository,cli,cloak,privacy
Classifier: Development Status :: 4 - Beta
Classifier: Environment :: Console
Classifier: Intended Audience :: Developers
Classifier: License :: OSI Approved :: MIT License
Classifier: Operating System :: OS Independent
Classifier: Programming Language :: Python :: 3
Classifier: Programming Language :: Python :: 3.9
Classifier: Programming Language :: Python :: 3.10
Classifier: Programming Language :: Python :: 3.11
Classifier: Programming Language :: Python :: 3.12
Classifier: Topic :: Security :: Cryptography
Classifier: Topic :: Software Development :: Version Control :: Git
Requires-Python: >=3.9
License-File: LICENSE
Requires-Dist: click>=8.0.0
Requires-Dist: rich>=13.0.0
Requires-Dist: questionary>=2.0.0
Requires-Dist: python-gnupg>=0.5.0
Requires-Dist: GitPython>=3.1.0
Requires-Dist: requests>=2.28.0
Requires-Dist: pyyaml>=6.0
Requires-Dist: tabulate>=0.9.0
Requires-Dist: watchdog>=3.0.0
Requires-Dist: colorama>=0.4.6
Requires-Dist: hakcer>=1.2.4
Provides-Extra: dev
Requires-Dist: pytest>=7.0.0; extra == "dev"
Requires-Dist: pytest-cov>=4.0.0; extra == "dev"
Requires-Dist: black>=23.0.0; extra == "dev"
Requires-Dist: isort>=5.12.0; extra == "dev"
Requires-Dist: mypy>=1.0.0; extra == "dev"
Requires-Dist: ruff>=0.1.0; extra == "dev"
Provides-Extra: docs
Requires-Dist: mkdocs>=1.5.0; extra == "docs"
Requires-Dist: mkdocs-material>=9.0.0; extra == "docs"
Dynamic: license-file
